scaffer/__init__.py
scaffer/__main__.py
scaffer/emitter.py
scaffer/scaffer.py
scaffer-3.0.dist-info/LICENSE
scaffer-3.0.dist-info/METADATA
scaffer-3.0.dist-info/WHEEL
scaffer-3.0.dist-info/entry_points.txt
scaffer-3.0.dist-info/top_level.txt
scaffer-3.0.dist-info/RECORD
