Metadata-Version: 2.1
Name: scaffer
Version: 3.0
Summary: scaffer
Classifier: Operating System :: OS Independent
Classifier: Programming Language :: Python
Classifier: Programming Language :: Python :: 3.10
Classifier: Programming Language :: Python :: 3.11
Requires-Python: >=3.10
License-File: LICENSE
Requires-Dist: argp
Requires-Dist: gitignore-parser
Requires-Dist: requests
